application/__init__.py
application/core/__init__.py
application/core/enums.py
application/core/mask_utils.py
application/core/replace_utils.py
application/core/utils.py
shieldb-0.4.9.data/data/README.md
shieldb-0.4.9.data/data/app.py
shieldb-0.4.9.data/data/requirements.txt
src/__init__.py
src/app.py
shieldb-0.4.9.dist-info/METADATA
shieldb-0.4.9.dist-info/WHEEL
shieldb-0.4.9.dist-info/entry_points.txt
shieldb-0.4.9.dist-info/top_level.txt
shieldb-0.4.9.dist-info/RECORD
